{"@context":"https://iiif.io/api/presentation/3/context.json","id":"https://abolitionimages.org//api/facet/medium/billboards.json","type":"Collection","label":{"none":["Billboards"]},"items":[{"id":"https://abolition-now.github.io/manifests/manifests/0246_hope.json","type":"Manifest","label":{"en":["Hope"]},"thumbnail":[{"id":"https://strob6zro3bzklrulaqu2545sy0odbvz.lambda-url.us-east-2.on.aws/iiif/3/0246_hope_oo.jpeg/full/612,408/0/default.jpg","type":"Image","height":408,"width":612,"service":[{"id":"https://strob6zro3bzklrulaqu2545sy0odbvz.lambda-url.us-east-2.on.aws/iiif/3/0246_hope_oo.jpeg","type":"ImageService3","profile":"level2"}],"format":"image/jpeg"}],"homepage":[{"id":"https://abolitionimages.org//works/hope","type":"Text","label":{"en":["Hope"]}}]}],"partOf":[{"id":"https://abolitionimages.org//api/facet/medium.json","type":"Collection"}],"summary":{"none":["Medium"]},"homepage":[{"id":"https://abolitionimages.org//search?medium=billboards","type":"Text","label":{"none":["Billboards"]}}]}