{"@context":"https://iiif.io/api/presentation/3/context.json","id":"https://abolitionimages.org//api/facet/subject/healthcare.json","type":"Collection","label":{"none":["Healthcare"]},"items":[{"id":"https://iiif.archive.org/iiif/an_0025_dismantledefund/manifest.json","type":"Manifest","label":{"none":["Dismantle I.C.E. Defund the Police"]},"thumbnail":[{"id":"https://iiif.archive.org/image/iiif/3/an_0025_dismantledefund%2F0025_dismantledefund_oo.jpg/full/360,/0/default.jpg","type":"Image","format":"image/jpeg","width":360,"height":360}],"homepage":[{"id":"https://abolitionimages.org//works/dismantle-ice-defund-the-police","type":"Text","label":{"none":["Dismantle I.C.E. Defund the Police"]}}]},{"id":"https://iiif.archive.org/iiif/an_0028_homelessvoices/manifest.json","type":"Manifest","label":{"none":["Homeless Voices for Justice"]},"thumbnail":[{"id":"https://iiif.archive.org/image/iiif/3/an_0028_homelessvoices%2F0028_homelessvoices_oo.jpg/full/360,/0/default.jpg","type":"Image","format":"image/jpeg","width":360,"height":283}],"homepage":[{"id":"https://abolitionimages.org//works/homeless-voices-for-justice","type":"Text","label":{"none":["Homeless Voices for Justice"]}}]},{"id":"https://iiif.archive.org/iiif/an_0321_wholearnsfromthis/manifest.json","type":"Manifest","label":{"none":["Who Learns From This?"]},"thumbnail":[{"id":"https://iiif.archive.org/image/iiif/3/an_0321_wholearnsfromthis%2F0321_wholearnsfromthis_oo.jpg/full/384,/0/default.jpg","type":"Image","format":"image/jpeg","width":384,"height":288}],"homepage":[{"id":"https://abolitionimages.org//works/who-learns-from-this","type":"Text","label":{"none":["Who Learns From This?"]}}]},{"id":"https://iiif.archive.org/iiif/an_0028_wontbesilent/manifest.json","type":"Manifest","label":{"none":["We Won't Be Silent Anymore"]},"thumbnail":[{"id":"https://iiif.archive.org/image/iiif/3/an_0028_wontbesilent%2F0028_wontbesilent_oo.jpg/full/512,/0/default.jpg","type":"Image","format":"image/jpeg","width":512,"height":512}],"homepage":[{"id":"https://abolitionimages.org//works/we-wont-be-silent-anymore","type":"Text","label":{"none":["We Won't Be Silent Anymore"]}}]},{"id":"https://iiif.archive.org/iiif/an_0318_whatwelose/manifest.json","type":"Manifest","label":{"none":["What We Lose"]},"thumbnail":[{"id":"https://iiif.archive.org/image/iiif/3/an_0318_whatwelose%2F0318_whatwelose_oo.jpg/full/512,/0/default.jpg","type":"Image","format":"image/jpeg","width":512,"height":512}],"homepage":[{"id":"https://abolitionimages.org//works/what-we-lose","type":"Text","label":{"none":["What We Lose"]}}]}],"partOf":[{"id":"https://abolitionimages.org//api/facet/subject.json","type":"Collection"}],"summary":{"none":["subject"]},"homepage":[{"id":"https://abolitionimages.org//search?subject=healthcare","type":"Text","label":{"none":["Healthcare"]}}]}