{"@context":"https://iiif.io/api/presentation/3/context.json","id":"https://abolitionimages.org//api/facet/visualmotifs/lyrics.json","type":"Collection","label":{"none":["Lyrics"]},"items":[{"id":"https://iiif.archive.org/iiif/an_0229_nothingburnsdown/manifest.json","type":"Manifest","label":{"none":["Nothing Burns Down"]},"thumbnail":[{"id":"https://iiif.archive.org/image/iiif/3/an_0229_nothingburnsdown%2F0229_nothingburnsdown_oo.jpeg/full/512,/0/default.jpg","type":"Image","format":"image/jpeg","width":512,"height":512}],"homepage":[{"id":"https://abolitionimages.org//works/nothing-burns-down","type":"Text","label":{"none":["Nothing Burns Down"]}}]}],"partOf":[{"id":"https://abolitionimages.org//api/facet/visualmotifs.json","type":"Collection"}],"summary":{"none":["visual_motifs"]},"homepage":[{"id":"https://abolitionimages.org//search?visualmotifs=lyrics","type":"Text","label":{"none":["Lyrics"]}}]}