{"@context":"https://iiif.io/api/presentation/3/context.json","id":"https://abolition-now.github.io/an/api/facet/photographer/aleksandar-dalek-dordevic.json","type":"Collection","label":{"none":["Aleksandar Dalek Dordevic"]},"items":[{"id":"https://raw.githubusercontent.com/markpbaggett/static_iiif/main/manifests/abolition_now/0007_gokupolicepigserbia_oo.jpg.json","type":"Manifest","label":{"en":["Das Drogen Police Dept"]},"thumbnail":[{"id":"https://strob6zro3bzklrulaqu2545sy0odbvz.lambda-url.us-east-2.on.aws/iiif/3/0007_gokupolicepigserbia_oo.jpg/full/540,360/0/default.jpg","type":"Image","height":360,"width":540,"service":[{"id":"https://strob6zro3bzklrulaqu2545sy0odbvz.lambda-url.us-east-2.on.aws/iiif/3/0007_gokupolicepigserbia_oo.jpg","type":"ImageService3","profile":"level2"}],"format":"image/jpeg"}],"homepage":[{"id":"https://abolition-now.github.io/an/works/das-drogen-police-dept","type":"Text","label":{"en":["Das Drogen Police Dept"]}}]}],"partOf":[{"id":"https://abolition-now.github.io/an/api/facet/photographer.json","type":"Collection"}],"summary":{"none":["Photographer"]},"homepage":[{"id":"https://abolition-now.github.io/an/search?photographer=aleksandar-dalek-dordevic","type":"Text","label":{"none":["Aleksandar Dalek Dordevic"]}}]}