{"@context":"https://iiif.io/api/presentation/3/context.json","id":"https://abolitionimages.org//api/facet/creator/critical-resistance.json","type":"Collection","label":{"none":["Critical Resistance "]},"items":[{"id":"https://iiif.archive.org/iiif/an_0121_0246_0247_peoplepower/manifest.json","type":"Manifest","label":{"none":["Building People Power"]},"thumbnail":[{"id":"https://iiif.archive.org/image/iiif/3/an_0121_0246_0247_peoplepower%2F0121_0246_0247_peoplepower_oo.jpeg/full/510,/0/default.jpg","type":"Image","format":"image/jpeg","width":510,"height":287}],"homepage":[{"id":"https://abolitionimages.org//works/building-people-power","type":"Text","label":{"none":["Building People Power"]}}]},{"id":"https://iiif.archive.org/iiif/an_0121_breaksthechain/manifest.json","type":"Manifest","label":{"none":["Breaks the Chains"]},"thumbnail":[{"id":"https://iiif.archive.org/image/iiif/3/an_0121_breaksthechain%2F0121_breaksthechain_oo.jpeg/full/375,/0/default.jpg","type":"Image","format":"image/jpeg","width":375,"height":164}],"homepage":[{"id":"https://abolitionimages.org//works/breaks-the-chains","type":"Text","label":{"none":["Breaks the Chains"]}}]},{"id":"https://iiif.archive.org/iiif/an_0121_nonewjails/manifest.json","type":"Manifest","label":{"none":["No New Jails NYC"]},"thumbnail":[{"id":"https://iiif.archive.org/image/iiif/3/an_0121_nonewjails%2F0121_nonewjails_oo.jpeg/full/512,/0/default.jpg","type":"Image","format":"image/jpeg","width":512,"height":394}],"homepage":[{"id":"https://abolitionimages.org//works/no-new-jails-nyc","type":"Text","label":{"none":["No New Jails NYC"]}}]}],"partOf":[{"id":"https://abolitionimages.org//api/facet/creator.json","type":"Collection"}],"summary":{"none":["creator"]},"homepage":[{"id":"https://abolitionimages.org//search?creator=critical-resistance","type":"Text","label":{"none":["Critical Resistance "]}}]}