{"@context":"https://iiif.io/api/presentation/3/context.json","id":"https://abolitionimages.org//api/facet/creator/no-letcher-prison.json","type":"Collection","label":{"none":["No Letcher Prison"]},"items":[{"id":"https://iiif.archive.org/iiif/an_0216_noletcherprisonhellbender/manifest.json","type":"Manifest","label":{"none":["Here's How"]},"thumbnail":[{"format":"image/jpeg","height":192,"id":"https://iiif.archive.org/image/iiif/2/an_0216_noletcherprisonhellbender%2f0216_noletcherprisonhellbender_oo_thumb.jpg/full/192,/0/default.jpg","service":[{"@id":"https://iiif.archive.org/image/iiif/2/an_0216_noletcherprisonhellbender%2F0216_noletcherprisonhellbender_oo_thumb.jpg","@type":"ImageService2","profile":"http://iiif.io/api/image/2/level2.json"}],"type":"Image","width":192},{"format":"image/jpeg","height":180,"id":"https://iiif.archive.org/image/iiif/2/an_0216_noletcherprisonhellbender%2f__ia_thumb.jpg/full/180,/0/default.jpg","service":[{"@id":"https://iiif.archive.org/image/iiif/2/an_0216_noletcherprisonhellbender%2F__ia_thumb.jpg","@type":"ImageService2","profile":"http://iiif.io/api/image/2/level2.json"}],"type":"Image","width":180}],"homepage":[{"id":"https://abolitionimages.org//works/heres-how","type":"Text","label":{"none":["Here's How"]}}]},{"id":"https://iiif.archive.org/iiif/an_0216_pizzanotprisons/manifest.json","type":"Manifest","label":{"none":["Pizza Not Prisons"]},"thumbnail":[{"format":"image/jpeg","height":192,"id":"https://iiif.archive.org/image/iiif/2/an_0216_pizzanotprisons%2f0216_pizzanotprisons_oo_thumb.jpg/full/192,/0/default.jpg","service":[{"@id":"https://iiif.archive.org/image/iiif/2/an_0216_pizzanotprisons%2F0216_pizzanotprisons_oo_thumb.jpg","@type":"ImageService2","profile":"http://iiif.io/api/image/2/level2.json"}],"type":"Image","width":192},{"format":"image/jpeg","height":180,"id":"https://iiif.archive.org/image/iiif/2/an_0216_pizzanotprisons%2f__ia_thumb.jpg/full/180,/0/default.jpg","service":[{"@id":"https://iiif.archive.org/image/iiif/2/an_0216_pizzanotprisons%2F__ia_thumb.jpg","@type":"ImageService2","profile":"http://iiif.io/api/image/2/level2.json"}],"type":"Image","width":180}],"homepage":[{"id":"https://abolitionimages.org//works/pizza-not-prisons","type":"Text","label":{"none":["Pizza Not Prisons"]}}]}],"partOf":[{"id":"https://abolitionimages.org//api/facet/creator.json","type":"Collection"}],"summary":{"none":["creator"]},"homepage":[{"id":"https://abolitionimages.org//search?creator=no-letcher-prison","type":"Text","label":{"none":["No Letcher Prison"]}}]}