{"@context":"https://iiif.io/api/presentation/3/context.json","id":"https://abolitionimages.org//api/facet/creator/omar-fathy.json","type":"Collection","label":{"none":["Omar Fathy"]},"items":[{"id":"https://iiif.archive.org/iiif/an_0157_acabcairo/manifest.json","type":"Manifest","label":{"none":["Combat"]},"thumbnail":[{"id":"https://iiif.archive.org/image/iiif/3/an_0157_acabcairo%2F0157_acabcairo_oo.jpg/full/474,/0/default.jpg","type":"Image","format":"image/jpeg","width":474,"height":316}],"homepage":[{"id":"https://abolitionimages.org//works/combat","type":"Text","label":{"none":["Combat"]}}]}],"partOf":[{"id":"https://abolitionimages.org//api/facet/creator.json","type":"Collection"}],"summary":{"none":["creator"]},"homepage":[{"id":"https://abolitionimages.org//search?creator=omar-fathy","type":"Text","label":{"none":["Omar Fathy"]}}]}