{"@context":"https://iiif.io/api/presentation/3/context.json","id":"https://abolitionimages.org//api/facet/creator/west-oakland-punks-with-lunch.json","type":"Collection","label":{"none":["West Oakland Punks with Lunch"]},"items":[{"id":"https://iiif.archive.org/iiif/an_0061_wekeepussafe/manifest.json","type":"Manifest","label":{"none":["Safety Slogans"]},"thumbnail":[{"id":"https://iiif.archive.org/image/iiif/3/an_0061_wekeepussafe%2F0061_wekeepussafe_oo.jpg/full/366,/0/default.jpg","type":"Image","format":"image/jpeg","width":366,"height":366}],"homepage":[{"id":"https://abolitionimages.org//works/safety-slogans","type":"Text","label":{"none":["Safety Slogans"]}}]}],"partOf":[{"id":"https://abolitionimages.org//api/facet/creator.json","type":"Collection"}],"summary":{"none":["creator"]},"homepage":[{"id":"https://abolitionimages.org//search?creator=west-oakland-punks-with-lunch","type":"Text","label":{"none":["West Oakland Punks with Lunch"]}}]}